Jcy_utils/__init__.py
Jcy_utils/core.py
jcy_utils-0.0.2.dist-info/METADATA
jcy_utils-0.0.2.dist-info/WHEEL
jcy_utils-0.0.2.dist-info/top_level.txt
jcy_utils-0.0.2.dist-info/RECORD
