Metadata-Version: 2.4
Name: Jcy_utils
Version: 0.0.2
Summary: A collection of image processing utilities for splitting, concatenation, and metrics calculation.
Author-email: Jiuchao Yao <1498225017@qq.com>
Project-URL: Homepage, https://github.com/yourusername/Jcy_utils
Classifier: Programming Language :: Python :: 3
Classifier: License :: OSI Approved :: MIT License
Classifier: Operating System :: OS Independent
Requires-Python: >=3.7
Requires-Dist: numpy
Requires-Dist: opencv-python
Requires-Dist: Pillow
Requires-Dist: tqdm
